{
    "albums": [
        {
            "release": "2013", 
            "artist": "Vulturius", 
            "cover": "http://api.jamendo.com/get2/image/album/redirect/?id=125880&imagesize=100", 
            "id": "125880", 
            "name": "Extra-Low-Vultage - Part 2"
        }, 
        {
            "release": "2012", 
            "artist": "David Voltage", 
            "cover": "http://api.jamendo.com/get2/image/album/redirect/?id=114295&imagesize=100", 
            "id": "114295", 
            "name": "La Vita \u00e8 Ora (EP)"
        }, 
        {
            "release": "2007", 
            "artist": "Mr. M (a.k.a. Dj KK7)", 
            "cover": "http://api.jamendo.com/get2/image/album/redirect/?id=13035&imagesize=100", 
            "id": "13035", 
            "name": "Distortion"
        }, 
        {
            "release": "2010", 
            "artist": "Batard Tronique", 
            "cover": "http://api.jamendo.com/get2/image/album/redirect/?id=70690&imagesize=100", 
            "id": "70690", 
            "name": "Go gorilla EP"
        }, 
        {
            "release": "2011", 
            "artist": "Tek E7", 
            "cover": "http://api.jamendo.com/get2/image/album/redirect/?id=93242&imagesize=100", 
            "id": "93242", 
            "name": "Troubadour"
        }, 
        {
            "release": "2008", 
            "artist": "dj Stonic", 
            "cover": "http://api.jamendo.com/get2/image/album/redirect/?id=31546&imagesize=100", 
            "id": "31546", 
            "name": "dj Stonic - Outronic"
        }, 
        {
            "release": "2011", 
            "artist": "Philippe LACOMBE", 
            "cover": "http://api.jamendo.com/get2/image/album/redirect/?id=94219&imagesize=100", 
            "id": "94219", 
            "name": "La jungle des mots"
        }, 
        {
            "release": "2008", 
            "artist": "Stellar Art Wars", 
            "cover": "http://api.jamendo.com/get2/image/album/redirect/?id=29630&imagesize=100", 
            "id": "29630", 
            "name": "The Albert Fish"
        }, 
        {
            "release": "2011", 
            "artist": "The X", 
            "cover": "http://api.jamendo.com/get2/image/album/redirect/?id=85573&imagesize=100", 
            "id": "85573", 
            "name": "DANZANTELECTRICO"
        }, 
        {
            "release": "2012", 
            "artist": "PremiumMusic (Instrumental Version)", 
            "cover": "http://api.jamendo.com/get2/image/album/redirect/?id=116590&imagesize=100", 
            "id": "116590", 
            "name": "Breakbeat Trip Hop Dubstep Drum And Bass Jungle Futuristic Dark Floors Album n\u00b0102"
        }, 
        {
            "release": "2012", 
            "artist": "PremiumMusic (Instrumental Version)", 
            "cover": "http://api.jamendo.com/get2/image/album/redirect/?id=116545&imagesize=100", 
            "id": "116545", 
            "name": "Futuristic Ambient Intelligent Drum and Bass Atmosphere Instrumental Album n\u00b080"
        }, 
        {
            "release": "2011", 
            "artist": "Out Of Orion (Ox3)", 
            "cover": "http://api.jamendo.com/get2/image/album/redirect/?id=98935&imagesize=100", 
            "id": "98935", 
            "name": "African Sun"
        }, 
        {
            "release": "2014", 
            "artist": "Arnoldsrecords", 
            "cover": "http://api.jamendo.com/get2/image/album/redirect/?id=134963&imagesize=100", 
            "id": "134963", 
            "name": "Jungle Train"
        }, 
        {
            "release": "2008", 
            "artist": "Xaviant Haze", 
            "cover": "http://api.jamendo.com/get2/image/album/redirect/?id=23807&imagesize=100", 
            "id": "23807", 
            "name": "Space Cake Breakz"
        }, 
        {
            "release": "2009", 
            "artist": "Junglist King", 
            "cover": "http://api.jamendo.com/get2/image/album/redirect/?id=55335&imagesize=100", 
            "id": "55335", 
            "name": "Jungle road part2"
        }, 
        {
            "release": "2009", 
            "artist": "Junglist King", 
            "cover": "http://api.jamendo.com/get2/image/album/redirect/?id=56716&imagesize=100", 
            "id": "56716", 
            "name": "Jungle road part 1"
        }, 
        {
            "release": "2011", 
            "artist": "Hardcore Scm", 
            "cover": "http://api.jamendo.com/get2/image/album/redirect/?id=94882&imagesize=100", 
            "id": "94882", 
            "name": "Hardcore Scm Mixed - Drum and Bass"
        }, 
        {
            "release": "2010", 
            "artist": "cybarasta", 
            "cover": "http://api.jamendo.com/get2/image/album/redirect/?id=58609&imagesize=100", 
            "id": "58609", 
            "name": "Babylone Tracks"
        }, 
        {
            "release": "2011", 
            "artist": "k Minus 1", 
            "cover": "http://api.jamendo.com/get2/image/album/redirect/?id=84692&imagesize=100", 
            "id": "84692", 
            "name": "Ladies Luv It"
        }, 
        {
            "release": "2008", 
            "artist": "mr dark", 
            "cover": "http://api.jamendo.com/get2/image/album/redirect/?id=33901&imagesize=100", 
            "id": "33901", 
            "name": "CLOSE"
        }, 
        {
            "release": "2008", 
            "artist": "Bionik Dread", 
            "cover": "http://api.jamendo.com/get2/image/album/redirect/?id=25055&imagesize=100", 
            "id": "25055", 
            "name": "hyper tension"
        }, 
        {
            "release": "2009", 
            "artist": "BLHD", 
            "cover": "http://api.jamendo.com/get2/image/album/redirect/?id=55780&imagesize=100", 
            "id": "55780", 
            "name": "ghosts remindings"
        }, 
        {
            "release": "2011", 
            "artist": "BLS", 
            "cover": "http://api.jamendo.com/get2/image/album/redirect/?id=92360&imagesize=100", 
            "id": "92360", 
            "name": "Arpodruma"
        }, 
        {
            "release": "2011", 
            "artist": "Luke Gooding", 
            "cover": "http://api.jamendo.com/get2/image/album/redirect/?id=95980&imagesize=100", 
            "id": "95980", 
            "name": "some Things"
        }, 
        {
            "release": "2010", 
            "artist": "AlexObiLives", 
            "cover": "http://api.jamendo.com/get2/image/album/redirect/?id=77738&imagesize=100", 
            "id": "77738", 
            "name": "My Oldschool Minutes"
        }, 
        {
            "release": "2007", 
            "artist": "Dub Lab", 
            "cover": "http://api.jamendo.com/get2/image/album/redirect/?id=9031&imagesize=100", 
            "id": "9031", 
            "name": "First Lick of Picon"
        }
    ], 
    "name": "Jungle"
}