{
    "name": "Baby - Be Anti Blues Yeah !!!", 
    "artist": "Pasqualino Fiorica", 
    "cover": "http://api.jamendo.com/get2/image/album/redirect/?id=20028&imagesize=400", 
    "tracks": [
        {
            "position": 1, 
            "mp3": "http://api.jamendo.com/get2/stream/track/redirect/?id=140079&streamencoding=mp31", 
            "name": "iveneverseenetbeforeyou"
        }, 
        {
            "position": 2, 
            "mp3": "http://api.jamendo.com/get2/stream/track/redirect/?id=140078&streamencoding=mp31", 
            "name": "dreamfullofcoffee"
        }, 
        {
            "position": 3, 
            "mp3": "http://api.jamendo.com/get2/stream/track/redirect/?id=140080&streamencoding=mp31", 
            "name": "new morning"
        }, 
        {
            "position": 4, 
            "mp3": "http://api.jamendo.com/get2/stream/track/redirect/?id=140082&streamencoding=mp31", 
            "name": "fromyourlips"
        }, 
        {
            "position": 5, 
            "mp3": "http://api.jamendo.com/get2/stream/track/redirect/?id=140081&streamencoding=mp31", 
            "name": "honey"
        }
    ], 
    "release": "2008", 
    "id": "20028"
}